{
  "generator-jhipster": {
    "promptValues": {
      "packageName": "com.mycompany.university",
      "nativeLanguage": "en"
    },
    "jhipsterVersion": "5.0.1",
    "applicationType": "monolith",
    "baseName": "university",
    "packageName": "com.mycompany.university",
    "packageFolder": "com/mycompany/university",
    "serverPort": "8080",
    "authenticationType": "jwt",
    "cacheProvider": "ehcache",
    "enableHibernateCache": true,
    "websocket": "spring-websocket",
    "databaseType": "sql",
    "devDatabaseType": "h2Disk",
    "prodDatabaseType": "mysql",
    "searchEngine": false,
    "messageBroker": false,
    "serviceDiscoveryType": false,
    "buildTool": "gradle",
    "enableSwaggerCodegen": false,
    "jwtSecretKey": "7fd02cbfb63cba6965f00f725a6b57d1b50093c8",
    "clientFramework": "angularX",
    "useSass": true,
    "clientPackageManager": "yarn",
    "testFrameworks": [
      "protractor"
    ],
    "jhiPrefix": "jhi",
    "enableTranslation": true,
    "nativeLanguage": "en",
    "languages": [
      "en",
      "ar-ly"
    ]
  }
}